{
  "signedContributors": [
    {
      "name": "guschmue",
      "id": 22941064,
      "comment_id": 736924989,
      "created_at": "2020-12-02T01:21:50Z",
      "repoId": 317424648,
      "pullRequestNo": 4
    },
    {
      "name": "petermattson",
      "id": 1,
      "comment_id": 1,
      "created_at": "2020-01-01T00:00:00Z",
      "repoId": 1,
      "pullRequestNo": 1
    },
    {
      "name": "sub-mod",
      "id": 7363264,
      "comment_id": 741356438,
      "created_at": "2020-12-09T00:59:17Z",
      "repoId": 317424648,
      "pullRequestNo": 8
    }
  ]
}
